resubmit/__bookkeeping.py
resubmit/__debug.py
resubmit/__init__.py
resubmit/__submit.py
resubmit-0.0.5.dist-info/licenses/LICENSE
resubmit-0.0.5.dist-info/METADATA
resubmit-0.0.5.dist-info/WHEEL
resubmit-0.0.5.dist-info/top_level.txt
resubmit-0.0.5.dist-info/RECORD
