Metadata-Version: 2.4
Name: resubmit
Version: 0.0.5
Summary: Small wrapper around submitit to simplify cluster submissions
Author: Amir Mehrpanah
License: MIT
License-File: LICENSE
Requires-Dist: submitit>=0.8
Provides-Extra: debug
Requires-Dist: debugpy; extra == "debug"
Dynamic: license-file
